EpubZhinanCongRumenDaoFangqiChini20190101/README.md
EpubZhinanCongRumenDaoFangqiChini20190101/__init__.py
EpubZhinanCongRumenDaoFangqiChini20190101/__main__.py
EpubZhinanCongRumenDaoFangqiChini20190101/file.epub
EpubZhinanCongRumenDaoFangqiChini20190101/index.html
EpubZhinanCongRumenDaoFangqiChini20190101/css/__init__.py
EpubZhinanCongRumenDaoFangqiChini20190101/css/annotations.css
EpubZhinanCongRumenDaoFangqiChini20190101/css/main.css
EpubZhinanCongRumenDaoFangqiChini20190101/css/normalize.css
EpubZhinanCongRumenDaoFangqiChini20190101/css/popup.css
EpubZhinanCongRumenDaoFangqiChini20190101/font/__init__.py
EpubZhinanCongRumenDaoFangqiChini20190101/font/fontello.eot
EpubZhinanCongRumenDaoFangqiChini20190101/font/fontello.svg
EpubZhinanCongRumenDaoFangqiChini20190101/font/fontello.ttf
EpubZhinanCongRumenDaoFangqiChini20190101/font/fontello.woff
EpubZhinanCongRumenDaoFangqiChini20190101/img/__init__.py
EpubZhinanCongRumenDaoFangqiChini20190101/img/annotator-glyph-sprite.png
EpubZhinanCongRumenDaoFangqiChini20190101/img/annotator-icon-sprite.png
EpubZhinanCongRumenDaoFangqiChini20190101/img/apple-touch-icon.png
EpubZhinanCongRumenDaoFangqiChini20190101/img/cancelfullscreen.png
EpubZhinanCongRumenDaoFangqiChini20190101/img/close.png
EpubZhinanCongRumenDaoFangqiChini20190101/img/fullscreen.png
EpubZhinanCongRumenDaoFangqiChini20190101/img/loader.gif
EpubZhinanCongRumenDaoFangqiChini20190101/img/menu-icon.png
EpubZhinanCongRumenDaoFangqiChini20190101/img/save.png
EpubZhinanCongRumenDaoFangqiChini20190101/img/saved.png
EpubZhinanCongRumenDaoFangqiChini20190101/img/settings-s.png
EpubZhinanCongRumenDaoFangqiChini20190101/img/settings.png
EpubZhinanCongRumenDaoFangqiChini20190101/img/star.png
EpubZhinanCongRumenDaoFangqiChini20190101/js/__init__.py
EpubZhinanCongRumenDaoFangqiChini20190101/js/epub.js
EpubZhinanCongRumenDaoFangqiChini20190101/js/epub.min.js
EpubZhinanCongRumenDaoFangqiChini20190101/js/epub.min.map
EpubZhinanCongRumenDaoFangqiChini20190101/js/hooks.min.js
epub_zhinan_cong_rumen_dao_fangqi_chini_20190101-2024.3.5.0.dist-info/METADATA
epub_zhinan_cong_rumen_dao_fangqi_chini_20190101-2024.3.5.0.dist-info/WHEEL
epub_zhinan_cong_rumen_dao_fangqi_chini_20190101-2024.3.5.0.dist-info/entry_points.txt
epub_zhinan_cong_rumen_dao_fangqi_chini_20190101-2024.3.5.0.dist-info/top_level.txt
epub_zhinan_cong_rumen_dao_fangqi_chini_20190101-2024.3.5.0.dist-info/RECORD
